client/__init__.py
client/client.py
client/client/__init__.py
client/client/add_contact.py
client/client/client_db.py
client/client/del_contact.py
client/client/main_window.py
client/client/main_window_btn.py
client/client/start_dialog.py
client/client/transport.py
client/common/__init__.py
client/common/decorators.py
client/common/descriptors.py
client/common/errors.py
client/common/metaclasses.py
client/common/utils.py
client/common/variables.py
client/logs/__init__.py
client/logs/client_log_config.py
client/logs/server_log_config.py
client/unit_tests/__init__.py
mess_client_jim-0.0.1.dist-info/METADATA
mess_client_jim-0.0.1.dist-info/WHEEL
mess_client_jim-0.0.1.dist-info/top_level.txt
mess_client_jim-0.0.1.dist-info/RECORD
